pymongo_smart_auth-2.1.3.dist-info/METADATA
pymongo_smart_auth-2.1.3.dist-info/WHEEL
pymongo_smart_auth-2.1.3.dist-info/entry_points.txt
pymongo_smart_auth-2.1.3.dist-info/licenses/LICENSE
pymongo_smart_auth/AsyncAuthMongoClient.py
pymongo_smart_auth/AuthMongoClient.py
pymongo_smart_auth/SmartAuth.py
pymongo_smart_auth/__init__.py
pymongo_smart_auth-2.1.3.dist-info/RECORD
