Metadata-Version: 2.1
Name: pymongo_smart_auth
Version: 2.1.3
Summary: This package extends PyMongo to provide built-in smart authentication.
Keywords: mongo,pymongo,authentication,seamless
Author-Email: Pierre-Louis Peeters <PLPeeters@users.noreply.github.com>
License: MIT
Project-URL: Homepage, https://github.com/PLPeeters/PyMongo-Smart-Auth
Requires-Python: >=3.6
Requires-Dist: pymongo<5,>3
